bootstrap.py
buildout.cfg
setup.py
src/gocept/__init__.py
src/gocept.lxml.egg-info/PKG-INFO
src/gocept.lxml.egg-info/SOURCES.txt
src/gocept.lxml.egg-info/dependency_links.txt
src/gocept.lxml.egg-info/namespace_packages.txt
src/gocept.lxml.egg-info/not-zip-safe
src/gocept.lxml.egg-info/requires.txt
src/gocept.lxml.egg-info/top_level.txt
src/gocept/lxml/README.txt
src/gocept/lxml/__init__.py
src/gocept/lxml/configure.zcml
src/gocept/lxml/ftesting.zcml
src/gocept/lxml/interfaces.py
src/gocept/lxml/objectify.py
src/gocept/lxml/tests.py
