Metadata-Version: 1.0
Name: gocept.lxml
Version: 0.2.1
Summary: Primarily proivdes zope3 interface definitions for lxml
Home-page: http://pypi.python.org/pypi/gocept.lxml
Author: Christian Zagrodnick
Author-email: cz@gocept.com
License: ZPL 2.1
Platform: UNKNOWN
